[
    {
        "language": "hebrew",
        "scripttype": "letter",
        "name": "ヘブライ文字",
        "letters":
        [
            {
                "id": 0,
                "name": "alef",
                "script": "א",
                "sofit": false,
                "dagesh": false,
                "original": 0,
                "explanation": "某宗教団体のことを思い出す人もいるかもしれないアレフ。ラテンアルファベットのAにあたる。Aの横画を突き出させて90°左に回せばそう見えないこともない。あるいは右下に小さく0とかけば数学における可算無限の濃度を表すことができる。何にせよせいぜい日常生活で触れることのできるヘブライ文字なんてアレフくらいだろう。斜めの線を最初に引くのがおすすめ。筆記体だとKにしか見えない。子音としてはア行の担当。つまり子音なし。"
            },
            {
                "id": 1,
                "name": "vet",
                "script": "ב",
                "sofit": false,
                "dagesh": false,
                "original": 1,
                "explanation": "ヴェート。あるいはヴェイトに聞こえる。バイトといえば家という単語になる。何となく家に見えなくもない。だけど完全にカタカナのユ。ユは二画だけど筆記体の時は右回りで一画で書いちゃう。後述のכと似てるんだけど下の線が独立して右に突き出してるのがヴェートです。筆記体の時はこのכと区別をつけるために下のあたりで一旦跳ねます。右上のところは丸く書いたほうがポイですよ。",
            },
            {
                "id": 2,
                "name": "bet",
                "script": "בּ",
                "sofit": false,
                "dagesh": true,
                "original": 1,
                "explanation": "ベート、あるいはベイト。בがvを担当するのに対し、ダゲッシュつきのבּの方はbを担当します。余談だが聖書はこの文字で始まる。vが重なるとbになるのか？　真ん中に点があるとかわいいよね。筆記体に点書いたらもうなんかネズミっぽいというか。",
            },
            {
                "id": 3,
                "name": "gimel",
                "script": "ג",
                "sofit": false,
                "dagesh": false,
                "original": 3,
                "explanation": "ギメル。大怪獣ギメルとでもいうべき荘厳な響き。しかしその実、ガマルといえばラクダの意味。お前...。גの見かけは何となく首をもたげているように見えるがラクダにしては後ろが短い。むしろ首を出したネッシー？　ギリシャ文字のガンマ（Γ,γ）にあたる文字なんだけどあんまり似てない。むしろ逆さ。そうか、逆さまのガンマなんだ。",
            },
            {
                "id": 4,
                "name": "dalet",
                "script": "ד",
                "sofit": false,
                "dagesh": false,
                "original": 4,
                "explanation": "ダレット。デレットといえば扉の意味。扉にしては線が足りないが。後述のרと似ているがこっちは角ばっていて、右に飛び出している。丸く描くとרで違う文字なので注意。二画に分けたほうがいいかも。カクカクしているという一点においてはギリシャ文字のデルタ（Δ）　に近いだろうか。あんまり真ん中に縦線を寄せてしまうとזと似てくるので注意。十分に横画を長くすること。順番に覚えるときは、個人的にはアレフからここまで四文字を一息で言いたい。「アレフ、ヴェート、ギメル、ダレット！」",
            },
            {
                "id": 5,
                "name": "hey",
                "script": "ה",
                "sofit": false,
                "dagesh": false,
                "original": 5,
                "explanation": "ヘイ。何と気の抜けた響き。同じ音でそのまま感嘆詞になる。もちろん意味は「ヘイ！」ヘイヘイヘイヘイ、マイムマイムマイムマイム...♪。左の縦線が長くなるとחと同じになってしまうので、全体の高さの半分くらいでいいと思われる。右上は尖ってても丸くても大丈夫。どうせ筆記体がすごく丸い。ちなみにこの文字一文字で定冠詞になる。",
            },
            {
                "id": 6,
                "name": "vav",
                "script": "ו",
                "sofit": false,
                "dagesh": false,
                "original": 6,
                "explanation": "ヴァヴ。かぎ針の意味。書体によっては上のほうが少しだけ左に曲がっていて、なおかぎ針らしい。問題はこの文字、長さで似てる文字に取り違えられる可能性がある。短いとיだし、長すぎるとןだ。通常の文字の大きさの上から下までちょうど。決して基準線の下まで伸ばしてはいけない。この一文字で接続詞「そして」の意味になる。確かに他の単語にちょっと「そして...」と付け足すには簡単だ。書くときは詰めて書いていい。",
            },
            {
                "id": 7,
                "name": "zain",
                "script": "ז",
                "sofit": false,
                "dagesh": false,
                "original": 7,
                "explanation": "ザイン。上にある横画は何となく右に下げておくと通。しかしどっこい、筆記体になるとむしろ一旦左に傾く。めっちゃ混乱する。Zと似てなくもない。ちょっとしたが足りないけど。しかし小文字のゼータ（ζ)と比べると...筆記体は完全に左右反転してるじゃないですか！　Tと似てるけど音が違うので注意。横幅は割と狭い。音読はここで第二区切り。一緒に声に出して。「ヘイ、ヴァヴ、ザイン！」",
            },
            {
                "id": 8,
                "name": "xet",
                "script": "ח",
                "sofit": false,
                "dagesh": false,
                "original": 8,
                "explanation": "ヘット。ただの「へ」ではない。喉の奥に息を当てるやつ。ドイツ語のchの音が近いらしい。הに似てるけど必ず左の縦線を上にくっつけること。そして縦線のほうが長く上に突き出しても可。筆記体だとむしろ積極的に突き出す。活字体でも上に出てる書体があった（気がする）。イメージとしては閉じてないとה（ヘイ）で力が抜けた音だけど、閉じると力が籠もってח（ヘット！）となる。イメージなので合わなかったら無視してください。",
            },
            {
                "id": 9,
                "name": "tet",
                "script": "ט",
                "sofit": false,
                "dagesh": false,
                "original": 9,
                "explanation": "テット。右回りにぐるっと一息に書いて上に投げる。ポーン。筆の始まりとくっつけて閉じてしまうとסになってしまうので注意。あくまで上は開けておく。なんか誰かの鼻みたいだよね。תと同じタ行を担当する子音だけど、現代の発音では多分二つに違いはない。綴りの違いとしてだけ意識して。",
            },
            {
                "id": 10,
                "name": "yud",
                "script": "י",
                "sofit": false,
                "dagesh": false,
                "original": 10,
                "explanation": "ユッド。ヨッド(yod)とも言う。子音としてはヤ行を担当。とにかく小さい。印刷で見るとなんかゴミなんじゃないかと思ったりするけどこれで一文字。一点と言うよりは、ちょっと左に払う。アポストロフィーみたいに一旦丸めたりはしない。短い縦線でもあり。上に行きすぎると違う記号(’)とかに見えてしまうので、あくまで他の文字の上はしと同じ高さから下げること。つまり「בּית」この高さ。例えば「תנ”ך」のように書くとこれは省略語を書くための記号になる。やっぱりちょっと丸いのが大事かも。",
            },
            {
                "id": 11,
                "name": "khaf",
                "script": "כ",
                "sofit": false,
                "dagesh": false,
                "original": 11,
                "explanation": "ハフ。この「ハ」もただのハじゃなくて喉を擦ってる感じ。いくらかkに近いけどkではない。実際現代のイスラエル人はח（ヘット）とכ（ハフ）の子音を区別はしていないらしい。聖書朗読するラビたちは区別しているのかもしれないが。カタカナのコに近いが、一角で右回りに書いたほうがいい。丸く書くのがおすすめだが、したの部分が足りないとרと区別が付かなくなる。十分に丸く囲んで。音読の区切りはここまで。「ヘット、テット、ユッド、ハフ！」",
            },
            {
                "id": 12,
                "name": "kaf",
                "script": "כּ",
                "sofit": false,
                "dagesh": true,
                "original": 11,
                "explanation": "カフ。掌、足の裏とかスプーンの意味。こっちは明確にカ行。こういうアン○ーンいそう。",
            },
            {
                "id": 13,
                "name": "khaf sofit",
                "script": "ך",
                "sofit": true,
                "dagesh": false,
                "original": 13,
                "explanation": "語末形（ソフィート）第一の刺客。כの折れ曲がっていた最後のカーブをまっすぐにして下に伸ばす。ノートの横線を突き刺す勢いで下に伸ばす。伸ばさないとרに見える。そもそもרとךの見分けつきます？　かなり初心者泣かせだが、あくまでכとセットで覚えたほうがいい。これに限らず、語末形は「最後のカーブを伸ばす」のが特徴。",
            },
            {
                "id": 14,
                "name": "lamed",
                "script": "ל",
                "sofit": false,
                "dagesh": false,
                "original": 14,
                "explanation": "ラメッド。何だか雷に見える。ラ行だけどLの音の方。Rは後で出てくる。この文字は他の文字に比べて上に突き出している。למדといった具合に。聖書ではこんなレベルではない、上の行よりもっと行ったんじゃないか、いやページから突き出したいんじゃないかってくらい上に伸びてる時がある。しかも曲がる。一応上から書くけど、筆記体のときは下から書く。",
            },
            {
                "id": 15,
                "name": "mem",
                "script": "מ",
                "sofit": false,
                "dagesh": false,
                "original": 15,
                "explanation": "メム。右回りに丸く書くやつと左上のちょっと出てるやつを分けて書く。筆記体は...どうしてこうなった？　Nやん。見た目はネズミ、あるいは尾根。何となく見つめられている気分になる。",
            },{
                "id": 16,
                "name": "mem sofit",
                "script": "ם",
                "sofit": true,
                "dagesh": false,
                "original": 16,
                "explanation": "語末形第二の刺客。原則と異なり、こいつは何だが四角くなる。左上から初めて右、下、左と一画で書いたのち、左上から下へ縦画を書いて閉じる。右上だけなんだが丸いように見えるが...。複数名詞がこれで終わるものが多いので結構頻繁に書くことになる文字。",
            },{
                "id": 17,
                "name": "nun",
                "script": "נ",
                "sofit": false,
                "dagesh": false,
                "original": 17,
                "explanation": "ヌン。聖書に出てくるフレーズで言うと「ヌンの子、ヨシュア」のヌン。ぬーん。横幅が狭いのが特徴。広いとכになってしまう。最後に左に出すのを忘れるとוと間違われる。通称ホッチキス。ננננננננ。ホッチキスといえば]のほうが有名かな。]]]]]]]]。大小様々なホッチキスがありますね。音読はここで区切り。実はラテンアルファベットのL、M、Nがここで続いている。「ラメッド、メム、ヌン！」",
            },
            {
                "id": 18,
                "name": "nun sofit",
                "script": "ן",
                "sofit": true,
                "dagesh": false,
                "original": 18,
                "explanation": "語末形第三の刺客。基準線を超えて下に突き刺す。結構長い。間違えやすいユッド、ヴァヴと並べるとיוןとなる。ほら、ヌンが一番長いでしょ？（狂気）語末形じゃないנの最後の曲がり角がまっすぐになったと考えて良い。",
            },
            {
                "id": 19,
                "name": "samekh",
                "script": "ס",
                "sofit": false,
                "dagesh": false,
                "original": 19,
                "explanation": "サメフ。上ないし左上から始めて右回りにぐるっと一回り、そして必ず閉じる。Oに見えるけど発音はS。ギリシャ文字のシグマ（σ）を知っていると、それと左右反転した形になっている。発音も同じ。何となく盾に見えるよね。あるいはコブラ。",
            },
            {
                "id": 20,
                "name": "ayin",
                "script": "ע",
                "sofit": false,
                "dagesh": false,
                "original": 20,
                "explanation": "アイン。泉の意味。もともとは喉をどうかする子音だったらしいけど現在では何もなし、ア行の発音。אと一緒。しかしそのもともとの子音は結構キツかったようで、「ソドム、ゴモラの街」と言う時の「ゴ」の音はこれ。どうして消えた。何となくyに見えるけど、右の縦線から書き始める。そして右の線が横向きになったところで左の縦線とくっつきたい。筆記体になるとガンマの小文字を逆から書いたみたいになる。",
            },
            {
                "id": 21,
                "name": "fey",
                "script": "פ",
                "sofit": false,
                "dagesh": false,
                "original": 21,
                "explanation": "フェー、あるいはフェイ。fの音を担当。ファ行だと思っていい。左上から下、右とクルクルしたところを先に書いてから、再度左上から始めて右回りにぐるっと書く。筆記体になるとなぜかクルクルは最後に移行。",
            },
            {
                "id": 22,
                "name": "pey",
                "script": "פּ",
                "sofit": false,
                "dagesh": true,
                "original": 21,
                "explanation": "ペー、あるいはペイ。口の意味。点を打つところ何となく迷うけど一画目が終わった延長線上に打っておくイメージ。",
            },
            {
                "id": 23,
                "name": "fey sofit",
                "script": "ף",
                "sofit": true,
                "dagesh": false,
                "original": 23,
                "explanation": "語末形第四の刺客。下に伸びる。ブッ刺さる。問題は筆記体の方で、なぜか上にト音記号みたいなのを生やす。したから書く。上行ってから下に戻ってくる時の結び方は色々あって小洒落てくる。初見でこれがףだと分かるやつはいないだろう。",
            },
            {
                "id": 24,
                "name": "tsadi",
                "script": "צ",
                "sofit": false,
                "dagesh": false,
                "original": 24,
                "explanation": "ツァディ。ひらがなの「と」かと思った？　ザーンネン、左右反転型でした！　実際これヘブライ文字自分なれてきたなと思っても間違える。書き順まで「と」と逆。つまり左上から初めて折れ曲がった線を先に書く。そして筆記体。どうして上に行こうと思った？　原型とどめてないが、他の文字の倍くらいの高さからグルグルする。דの筆記体は大体他の文字と同じ高さからグルグルする。何だかロシア語で似たようなの見た気がするけど気のせい。音読の区切り。「サメフ、アイン、フェー、ツァディ！」",
            },
            {
                "id": 25,
                "name": "tsadi sofit",
                "script": "ץ",
                "sofit": true,
                "dagesh": false,
                "original": 25,
                "explanation": "語末形最後の刺客。最初の斜めからの折れ曲がり線がまっすぐになってしかも下向きに直ってる。深く突き刺した後に枝をつける。そして筆記体はそれの反動だろうか。高く浮かび上がった上に頭上で輪を描いてしまった。これもいろんな書体があるけどとりあえず上の方で丸くなってたらツァディの語末形。何となく下に戻ってきてたらフェーの語末形。",
            },
            {
                "id": 26,
                "name": "quf",
                "script": "ק",
                "sofit": false,
                "dagesh": false,
                "original": 26,
                "explanation": "クフ。コフとも言う。コフは猿の意味。だんだん猿の頭に見えてきた。アルファベットではqで転写するけど発音は多分kで大丈夫。qっていうよりはpだよね。それからカタカナの「ア」に見える。書き順もアでok。下に突き刺さっている。",
            },
            {
                "id": 27,
                "name": "resh",
                "script": "ר",
                "sofit": false,
                "dagesh": false,
                "original": 27,
                "explanation": "レーシュ。ローシュというと頭の意味。Rの音担当で、巻き舌でもあり。rと逆向きだ。まあそんなもんだよね。",
            },
            {
                "id": 28,
                "name": "shin",
                "script": "שׁ",
                "sofit": false,
                "dagesh": false,
                "original": 28,
                "explanation": "シン。shの音担当。右上に点がついてるけど、これはダゲッシュではなくて（ダゲッシュがつく可能性もあるけどそれは真ん中にくる）、次のスィンと区別するための点。ヘブライ語は古くからsとshの区別があったようで、「お前、シボレテ(שׁבלת)って言ってみろ。（言えなくてスィボレテになったらお前は外国人だ）」という話が聖書に残っている。書き方は右上から下を通って左上まで器を作り、真ん中の線を最後に足す。筆記体ではその作業を一まとめにして右回りに一画で書く。",
            },
            {
                "id": 29,
                "name": "sin",
                "script": "שׂ",
                "sofit": false,
                "dagesh": false,
                "original": 29,
                "explanation": "スィン。こっちは左上に点がある。סと音がかぶるけど多分区別はない。辞書だとこの二つが違う文字として並んでる時（つまりシンで始まる単語が全て終わってからスィンが語頭の単語が始まる）もあるので注意して。",
            },
            {
                "id": 30,
                "name": "tav",
                "script": "ת",
                "sofit": false,
                "dagesh": false,
                "original": 30,
                "explanation": "タブ。印の意味。左上から右に伸びる画を最初に書く。左の縦線はそのまま下ろしてもいいけど、最後左に少し伸ばして足を作ると区別しやすい。筆記体になると天辺が尖って三角になる。さあ一緒に声を出して。「クフ、レーシュ、シン、タヴ！」",
            },
        ],
    },
    {
        "language": "hebrew",
        "scripttype": "vowel simbol",
        "name": "ヘブライ語母音記号",
        "pickers": [
            {
                "id": 0,
                "name": "a",
            },
            {
                "id": 1,
                "name": "i",
            },
            {
                "id": 2,
                "name": "u",
            },
            {
                "id": 3,
                "name": "e",
            },
            {
                "id": 4,
                "name": "o",
            },
            {
                "id": 5,
                "name": "a/o",
            },
            {
                "id": 6,
                "name": "ə/[no vowel]",
            },
        ],
        "letters": [
            {
                "id": 0,
                "name": "qamats",
                "answerId": 5,
                "script": "אָ",
                "explanation": "カマツ。発音が文脈に応じて二種類あるので、aと発音する方をカマツ・ガドール（大きいカマツ）、oと発音する方をカマツ・カタン（小さいカマツ）と呼ぶ。大体はaの方なのでとりあえずaと思っていてもいい。横線がある母音記号は大体a。",
            },
            {
                "id": 1,
                "name": "patax",
                "answerId": 0,
                "script": "אַ",
                "explanation": "パタフ。aの母音を担当。昔はカマツより短い音だったよう。そのせいかパタフが変化してカマツになったり、カマツが変化してパタフになったりよくする。現代では同じような長さで発音される。謎の文法事項「潜入パタフ」においてだけは子音より先にaと発音する。",
            },
            {
                "id": 2,
                "name": "xataf patax",
                "answerId": 0,
                "script": "אֲ",
                "explanation": "ハタフ・パタフ。ハタフとは他の母音記号にくっつくシェバー（複合シェバー）、つまり縦に二つ並んでいる点々を指す。これがつくと母音が短くなるってことになっているけど、例によって実際の発音では変わらない。これもa。複合シェバーは主には喉音という種類の子音文字につく。",
            },
            {
                "id": 3,
                "name": "tsere male",
                "answerId": 3,
                "script": "אֵי",
                "explanation": "ツェレー・マレー。eの発音。יがついているが、これは母音の表記を補助しているもので、子音ではない。逆に、母音記号がついていない文章を読むときに、子音でなさそうなיが出てきたらこれの可能性がある。マレーというのは満ちているという意味で、補助の文字を入れていることを表す。横に点が並ぶと大体e。",
            },
            {
                "id": 4,
                "name": "tsere xaser",
                "answerId": 3,
                "script": "אֵ",
                "explanation": "ツェレー・ハセル。ハセルは欠けている、という意味。発音はマレーとハセルで変わらない。これもe。",
            },
            {
                "id": 5,
                "name": "segol",
                "answerId": 3,
                "script": "אֶ",
                "explanation": "セゴール。eの発音。ツェレーに一点足した形なのでこれもeと覚えたい。",
            },
            {
                "id": 6,
                "name": "xataf segol",
                "answerId": 3,
                "script": "אֱ",
                "explanation": "ハタフ・セゴール。ハタフがついても発音は同じ。",
            },
            {
                "id": 7,
                "name": "xiriq male",
                "answerId": 1,
                "script": "אִי",
                "explanation": "ヒレク・マレー。iの発音。יがついていると大体ヒレクを疑っていいと思う。",
            },
            {
                "id": 8,
                "name": "xiriq xaser",
                "answerId": 1,
                "script": "אִ",
                "explanation": "ヒレク・ハセル。ヒレクのיが見えないバージョン。",
            },
            {
                "id": 9,
                "name": "xolam male",
                "answerId": 4,
                "script": "אוֹ",
                "explanation": "ホラム・マレー。文字の上に点があるとo。なぜかוが入ると母音記号はוのところにつく。",
            },
            {
                "id": 10,
                "name": "xolam xaser",
                "answerId": 4,
                "script": "אֹ",
                "explanation": "ホラム・ハセル。ホラムのוが見えないバージョン。",
            },
            {
                "id": 11,
                "name": "xataf qamats",
                "answerId": 4,
                "script": "אֳ",
                "explanation": "ハタフ・カマツ。これだけはハタフがつくと発音が変わる、というかa/oのどちらかだったのが明確にoだけになる。多分短くなるからだと思う（適当）。",
            },
            {
                "id": 12,
                "name": "shuruq",
                "answerId": 2,
                "script": "אוּ",
                "explanation": "シュルク。今までの法則に当てはまらないのがuです。なぜかוの横につきます。これのせいで「母音記号は子音の下に付きます」とか「主に下、例外的に上にも」などと言えない。「母音記号は基本的に下についてますがוにつくものだけは上にも横にも付きます！」という状況になる。本当ヘブライ語って例外だらけだよね。ちなみにホラム・マレーは単独(וֹ)では現れないのだけど、こっちは前置詞のוにつく形で単独（וּ）でも現れる。",
            },
            {
                "id": 13,
                "name": "qubuts",
                "answerId": 2,
                "script": "אֻ",
                "explanation": "クブツ。あんまり見ないけどこれはu。",
            },
            {
                "id": 14,
                "name": "sheva",
                "answerId": 6,
                "script": "אְ",
                "explanation": "シェバー。有音と無音があって、有音の時は半母音と呼ばれる弱い音、無音の時はその上の子音だけを発音する。いつ無音でいつ有音なのかは頑張って単語の中で覚えてってください。原則としては、音節の最初（特に単語の最初）は有音です。これ、便宜上アレフの下に書いたけど多分アレフにシェバーがつくことって無い？　とにかく文字の下のこの位置にきます！",
            },
        ],
    },
    
]

